metaflow_extensions/snowflake/plugins/constants.py
metaflow_extensions/snowflake/plugins/exceptions.py
metaflow_extensions/snowflake/plugins/mfextinit_snowflake.py
metaflow_extensions/snowflake/plugins/snowflake.py
metaflow_extensions/snowflake/toplevel/__init__.py
metaflow_extensions/snowflake/toplevel/toplevel.py
metaflow_snowflake-0.0.1.dist-info/LICENSE
metaflow_snowflake-0.0.1.dist-info/METADATA
metaflow_snowflake-0.0.1.dist-info/WHEEL
metaflow_snowflake-0.0.1.dist-info/top_level.txt
metaflow_snowflake-0.0.1.dist-info/RECORD
